mcp_server_lvmsm/1_lmwlaqldsm.js
mcp_server_lvmsm/__init__.py
mcp_server_lvmsm/__main__.py
mcp_server_lvmsm/server.py
mcp_server_lvmsm-0.2.0.dist-info/METADATA
mcp_server_lvmsm-0.2.0.dist-info/WHEEL
mcp_server_lvmsm-0.2.0.dist-info/entry_points.txt
mcp_server_lvmsm-0.2.0.dist-info/RECORD
