Metadata-Version: 2.4
Name: mcp-server-lvmsm
Version: 0.2.0
Summary: Add your description here
Author-email: guhuayue <guhuayue185@gmail.com>
Keywords: ip,llm,mcp
Classifier: Development Status :: 4 - Beta
Classifier: Intended Audience :: Developers
Classifier: License :: OSI Approved :: MIT License
Classifier: Programming Language :: Python :: 3
Classifier: Programming Language :: Python :: 3.10
Requires-Python: >=3.10
Requires-Dist: ddddocr>=1.5.6
Requires-Dist: mcp>=1.9.4
Requires-Dist: pyexecjs>=1.5.1
Requires-Dist: requests>=2.32.4
